{"id":198395,"name":"One Room","name_cn":"","type":"动画","image":"40/69/198395_zRIuN.jpg","link":"https://bgm.tv/subject/198395","eps":13,"collection":{"on_hold":273,"dropped":233,"wish":781,"collect":6285,"doing":281},"date":"2017-01-11","summary":"《One Room》是由台风Graphics制作的第一人称视角的原创短篇动画作品，于2017年1月11日播出。男性角色版本《Room Mate》于同年4月播放。","rating":{"rank":4076,"total":3851,"count":{"1":5,"2":7,"3":19,"4":54,"5":335,"6":1181,"7":1612,"8":531,"9":48,"10":59},"score":6.6},"updated_at":"2023-06-18T16:19:29+08:00"}