{"id":228254,"name":"デート・ア・ライブⅢ","name_cn":"约会大作战 第三季","type":"动画","image":"73/8c/228254_X7Y56.jpg","link":"https://bgm.tv/subject/228254","eps":12,"collection":{"on_hold":252,"dropped":454,"wish":513,"collect":5327,"doing":214},"date":"2019-01-11","summary":"人類は『空間震』と呼ばれる新たな災害に見舞われていた。\r\n空間を揺るがし、あらゆるものを破壊し尽くすその災厄は、\r\n精霊と呼ばれる存在が臨界から顕現することにより発生するものだった。\r\n空間震を止め、災厄を人類から退けるために必要とされる措置は、\r\n武力をもって精霊を殲滅する、もしくは——\r\n\r\n『デートしてデレさせる』！\r\n\r\n精霊をデレさせ、更に『キス』をすることでその力を封印できる——\r\nそんな能力を持っている高校生・五河士道。\r\n人類の平和のため、なにより精霊たちを救うため——\r\n士道は彼女たちとの『デート』に奔走する。\r\n士道に心を開いた精霊・十香、四糸乃、琴里、耶具矢、夕弦、美九。\r\n精霊を殲滅するべく動く＜ＡＳＴ＞。精霊を利用せんとする＜ＤＥＭ＞。\r\n精霊との対話を試みる＜ラタトスク＞。\r\nそして、デレさせるべき新たな精霊——\r\nすべてを巻き込み、新たな戦争＜デート＞が始まる——","rating":{"rank":7797,"total":3318,"count":{"1":75,"2":106,"3":294,"4":735,"5":901,"6":766,"7":284,"8":93,"9":21,"10":43},"score":5},"updated_at":"2023-06-18T16:30:23+08:00"}