{"id":297361,"name":"チート薬師のスローライフ～異世界に作ろうドラッグストア～","name_cn":"开挂药师的异世界悠闲生活～在异世界开药店吧～","type":"动画","image":"d2/b0/297361_ALyM7.jpg","link":"https://bgm.tv/subject/297361","eps":12,"collection":{"on_hold":151,"dropped":358,"wish":270,"collect":1164,"doing":179},"date":"2021-07-07","summary":"社畜として日々働くだけの男、桐尾礼治。\r\n\r\n今日もうつろな目で会社に向かって歩いていたらいつの間にか異世界の森にいた。\r\n\r\n…あぁ、これが流行りの異世界転生か。\r\n\r\n持っていたスキルは「鑑定、創薬」の2種類。\r\nあれたいしたことない・・・、でもいっか。\r\n\r\nそう考えていたけど、思った以上にチートなスキルだということが判明！\r\n\r\nその世界にはなかった回復薬などを次々と製造し、あっという間に一儲け。\r\n\r\nもう社蓄として働くなんてまっぴらごめん！\r\n\r\n悠々自適なスローライフを送ろうと決意し、\r\nドラッグストアをオープンさせる。\r\n\r\n異世界のドラッグストアを舞台にしたスローライフの物語が始まる。","rating":{"rank":7340,"total":866,"count":{"1":6,"2":14,"3":39,"4":101,"5":224,"6":303,"7":127,"8":34,"9":4,"10":14},"score":5.6},"updated_at":"2023-06-18T16:05:47+08:00"}