{"id":309311,"name":"Cyberpunk: Edgerunners","name_cn":"赛博浪客","type":"动画","image":"39/83/309311_dJU58.jpg","link":"https://bgm.tv/subject/309311","eps":10,"collection":{"on_hold":202,"dropped":118,"wish":1843,"collect":15166,"doing":961},"date":"2022-09-13","summary":"《赛博朋克：浪客》是与《赛博朋克2077》共享同一世界观的原创动画项目，为一部十集的独立故事剧集，讲述了一名街头小子尝试在技术高度繁荣、人体改造盛行的未来城市中挣扎求生的故事。冒着失去一切的风险，他选择成为一名浪客 —— 游走于法外的雇佣兵。\r\n\r\n据介绍，该动画剧集将是一个与游戏《赛博朋克2077》剧情完全不同的独立故事，舞台依然是夜之城，但会有新的角色新的剧情，并非将游戏故事再演绎一次。","rating":{"rank":124,"total":11601,"count":{"1":20,"2":12,"3":16,"4":40,"5":119,"6":437,"7":1712,"8":4672,"9":3408,"10":1165},"score":8.2},"updated_at":"2023-06-18T15:40:40+08:00"}