{"id":349039,"name":"魔法少女マジカルデストロイヤーズ","name_cn":"魔法少女毁灭者","type":"动画","image":"7c/bd/349039_b4QZQ.jpg","link":"https://bgm.tv/subject/349039","eps":12,"collection":{"on_hold":250,"dropped":757,"wish":589,"collect":1369,"doing":751},"date":"2023-04-07","summary":"2008年——因神秘的势力出现，动画、游戏、漫画、音乐、铁路、cosplay等所有御宅文化在日本被清除殆尽。收容相关商品、以保护的名义镇压御宅族。人们像是失去了自我般没有质疑。本以为御宅族被负责掌管秩序的组织“SSC”蹂躏灭亡。但是，夺回了被封锁的秋叶原、高举反旗的人出现了。\r\n年轻的革命者“御宅英雄”——比谁都热爱御宅文化，比谁都热爱秋叶原的男人。还有仰慕他的三个魔法少女——“ANARCHY”“BLUE”“PINK”。\r\n以2011年的日本为舞台，聚集在自由之旗下的御宅族们——秋叶原革命军，将与SSC首领“SHOBON”展开壮烈的战争。\r\n混沌和秩序都被破坏，为了能说出尽情喜欢自己喜欢的东西的世界。\r\n聚集在自由旗帜下的御宅族们，为了取回被夺走的文化，掀起OTAKU COUNTER CULTURE。","rating":{"rank":7722,"total":1450,"count":{"1":40,"2":58,"3":131,"4":240,"5":343,"6":386,"7":175,"8":56,"9":13,"10":8},"score":5.1},"updated_at":"2023-06-18T15:39:36+08:00"}