{"id":37873,"name":"CLANNAD もうひとつの世界 智代編","name_cn":"CLANNAD 另一个世界 智代篇","type":"动画","image":"7f/ec/37873_ZyP2G.jpg","link":"https://bgm.tv/subject/37873","eps":1,"collection":{"on_hold":97,"dropped":44,"wish":736,"collect":8792,"doing":46},"date":"2008-07-16","summary":"每天浑浑噩噩，除了迟到便是逃学，被同学当作不良少年的光坂高中学生冈崎朋也在这一过程中和温柔美丽的女孩坂上智代熟稔，不知不觉便成为恋人。青春的爱恋平淡，却不乏幸福可言。未过多久，智代当选学生会长，在得到同学们祝贺的同时，他和朋也看似并不搭调的关系引来周围的风言风语，甚至连校长也给予特别的关注。在随后的日子里，朋也与智代不得不疏远起来，他们很少能够找到见面聊天的机会。似乎因为朋也的原因，智代作为学生会长遭受越来越多的非议，这一切迫使朋也要认真考虑，是否该和智代拉开距离……","rating":{"rank":553,"total":5325,"count":{"1":12,"2":5,"3":6,"4":19,"5":93,"6":471,"7":1575,"8":2176,"9":579,"10":389},"score":7.7},"updated_at":"2023-06-18T17:32:16+08:00"}