{"id":411974,"name":"声優ラジオのウラオモテ","name_cn":"声优广播的台前幕后","type":"动画","image":"7b/a0/411974_MKw1Y.jpg","link":"https://bgm.tv/subject/411974","eps":12,"collection":{"on_hold":170,"dropped":481,"wish":470,"collect":1683,"doing":703},"date":"2024-04-10","summary":"“夕阳和～”“安美的！”“高中生广播~！”\r\n“本节目是由碰巧就读于同一所高中、同一个班级的我们，为大家带来教室氛围的节目！”无论是作为配音员还是作为同班同学都关系极好的二人，放松地做配音员广播，但这仅仅是“台前”的模样。夕阳的本性是阴沉的土妹子，而安美则是地道的辣妹。容貌和性格都正好相反的二人，一开口就要吵架。“……怎么这么晃眼。你这样跟平时形象的差别真的大到吓人，平时的阴沉都到哪去了？”“你才是，别用这副模样发出可爱的声音啊。”录音结束后便就地变成修罗场，挖苦和谩骂势如风暴。\r\n和这种人一起做广播，我绝对办不到！但是，节目可不会等人，前途坎坷的配音员广播，会持续多久……\r\n靠职业精神欺骗全世界，暴露就要结束的青春配音员节目，现已播出。","rating":{"rank":7811,"total":1560,"count":{"1":8,"2":19,"3":59,"4":157,"5":375,"6":595,"7":286,"8":46,"9":6,"10":9},"score":5.6},"updated_at":"2024-09-15T17:27:34+08:00"}