{"id":415182,"name":"好きな子がめがねを忘れた","name_cn":"喜欢的人忘记戴眼镜了","type":"动画","image":"65/04/415182_yQYFE.jpg","link":"https://bgm.tv/subject/415182","eps":13,"collection":{"on_hold":221,"dropped":768,"wish":606,"collect":763,"doing":1142},"date":"2023-07-04","summary":"这是一段由裸视距离开始的恋情。\r\n有点内向的初中男生小村，喜欢坐在邻座戴着眼镜的三重同学。“真想跨过这层厚厚的镜片，去看三重同学那双漂亮的眼睛。”小村被三重同学那神奇的魅力所吸引，却始终不敢开口跟她说话。这样的三重同学，其实是个常常忘记戴眼镜的天然呆女生。就在分班后的第三天，小村看见面有难色的三重同学而尽力帮助她，面对拼命想看清楚的三重同学，小村因距离过近而心跳不已。","rating":{"rank":7519,"total":1185,"count":{"1":32,"2":27,"3":67,"4":160,"5":286,"6":347,"7":179,"8":57,"9":8,"10":22},"score":5.4},"updated_at":"2023-06-18T17:50:13+08:00"}