{"id":424227,"name":"【推しの子】Mother and Children","name_cn":"【我推的孩子】Mother and Children","type":"动画","image":"69/1e/424227_OhkuW.jpg","link":"https://bgm.tv/subject/424227","eps":1,"collection":{"on_hold":34,"dropped":51,"wish":331,"collect":3145,"doing":153},"date":"2023-03-17","summary":"「かぐや様は告らせたい」の赤坂アカ原作、「クズの本懐」の横槍メンゴ作画による「週刊ヤングジャンプ」連載の人気コミックを原作とする2023年4月放送開始のテレビアニメ「【推しの子】」の第1話（90分拡大版）を放送に先駆けて劇場上映。\r\n\r\nとある地方都市の病院に勤める産婦人科医・ゴロー。ある日、ゴローの推しアイドルである「B小町」のアイが彼の診察室に現れる。アイはある秘密を抱えており、ゴローは彼女との“最悪”の出会いをきっかけに数奇な運命に巻き込まれていく。\r\n\r\n「可愛いだけじゃない式守さん」などの動画工房がアニメーション制作を手がけ、「私に天使が舞い降りた！」の平牧大輔が監督、「彼女、お借りします」の平山寛菜がキャラクターデザインを担当。","rating":{"rank":420,"total":2203,"count":{"1":9,"2":9,"3":13,"4":12,"5":55,"6":159,"7":474,"8":903,"9":408,"10":161},"score":7.8},"updated_at":"2023-06-18T15:05:39+08:00"}