{"id":82777,"name":"やはり俺の青春ラブコメはまちがっている。 OVA","name_cn":"我的青春恋爱物语果然有问题 OVA","type":"动画","image":"81/c0/82777_78uUP.jpg","link":"https://bgm.tv/subject/82777","eps":1,"collection":{"on_hold":71,"dropped":24,"wish":430,"collect":7131,"doing":57},"date":"2013-09-19","summary":"PSV游戏「果然在游戏里我的青春恋爱物语也有问题。」2013年9月19日发售，限定版将同捆原作者渡航担任脚本的新作OVA，讲述TV动画中未播出的番外篇故事。","rating":{"rank":1838,"total":3876,"count":{"1":5,"2":4,"3":9,"4":17,"5":139,"6":636,"7":1769,"8":1015,"9":132,"10":150},"score":7.2},"updated_at":"2023-06-18T15:12:09+08:00"}